{"hasMore":true,"list":[{"id":1,"title":"烤鱼","score":"8.1","collection":false,"cooked":"50136","titlebg":"/images/fish/1.jpg","detail":{"detailImg":"/images/fish/detail/2.jpg","steps":[{"title":"步骤1","content":"在生鸡翅上划刀，用一勺老抽，两勺料酒腌至少两小时 【时间紧可省略腌制，但要划刀】"},{"title":"步骤2","content":"锅中放水和葱姜片，鸡翅下锅煮开，捞出，用冷水冲洗掉浮沫，沥干"},{"title":"步骤3","content":"一听可乐、一大勺料酒、一勺老抽，两勺生抽，加一点盐。加半支桂皮会更有风味。炖至汤汁还剩一碗水的量时，再尝尝咸淡，如需加盐再加少量盐，这样不容易出差错。"},{"title":"步骤4","content":"炖至汤汁收浓，浓度看图，基本所有汁都裹在鸡翅上了，只剩约三勺汤汁了，出锅"}]}},{"id":2,"title":"剁椒鱼头","score":"8.5","collection":false,"cooked":"41474","titlebg":"/images/fish/3.jpg","detail":{"detailImg":"/images/fish/detail/4.jpg","steps":[{"title":"步骤1","content":"猪小排冼净，晾干水份备用"},{"title":"步骤2","content":"锅内倒少量油，烧热之后，爆香姜片"},{"title":"步骤3","content":"放入排骨，一直煸炒到排骨变色后，表面金黄微焦"},{"title":"步骤4","content":"此时就可以放入黄金比例中的调料了，顺序是：先放一汤勺料酒，接着两汤勺酱油，三汤勺米醋最后四汤勺白糖，炒匀"},{"title":"步骤5","content":"再倒入能没过排骨的开水，调中小火焖20分钟"},{"title":"步骤6","content":"20分钟后调入盐，开大火收汁，收到汁浓色亮时，撒入芝麻点缀即可出锅（锅里剩下的姜片丢掉不用，最后大火收汁时注意多翻动锅内的排骨，避免烧焦哟！）"}]}},{"id":3,"title":"清蒸老头鱼","score":"8.7","collection":false,"cooked":"19071","titlebg":"/images/fish/5.jpg","detail":{"detailImg":"/images/fish/detail/6.jpg","steps":[{"title":"步骤1","content":"新鲜对虾，剪去须、爪、嘴，以整齐美观，入口方便"},{"title":"步骤2","content":"从背部剪开，至尾端，挑去黑线。剪口不要正中，偏一点为宜，以免破坏黑线"},{"title":"步骤3","content":"清洗干净，控净水分备用。姜蒜切细（约1:3），香葱切段"},{"title":"步骤4","content":"锅中多倒油，烧至约6、7成热，投入大虾，迅速翻面，变红起酥即捞出"},{"title":"步骤5","content":"锅中留少许油，下姜蒜炒香，中火，下番茄酱（约3小匙），或去皮切碎的西红柿（只要约3小匙的量），炒出红油"},{"title":"步骤6","content":"投入大虾，沿锅边烹入少许料酒、生抽（不能是深色酱油），洒入约3小匙白糖，以炒勺轻压几下虾脑，挤出红汁，大火炒匀，倒入约小半碗温水，大火烧开，小火盖闷"},{"title":"步骤7","content":"约1、2分钟后，开盖，投入葱段，加盐调味，大火收汁，约20来秒，见汤汁收紧、油亮、颜色变深时，即可出锅"}]}},{"id":4,"title":"红烧带鱼的做法","score":"7.7","collection":false,"cooked":"16392","titlebg":"/images/fish/7.jpg","detail":{"detailImg":"/images/fish/detail/8.jpg","steps":[{"title":"步骤1","content":"准备材料，小葱切小段"},{"title":"步骤2","content":"锅中热油，炒熟肉沫，盛起来搁置"},{"title":"步骤3","content":"锅中再备油，炒香豆瓣"},{"title":"步骤4","content":"加入水，再放入花椒粒、辣椒粉、胡椒末，小火煮7分钟，加入炒好的肉沫"},{"title":"步骤5","content":"豆腐划成小块放入"},{"title":"步骤6","content":"煮几分钟即可"},{"title":"步骤7","content":"倒入水淀粉，再煮开汤汁"},{"title":"步骤8","content":"盛起来，撒上花椒末，再撒上葱花即可"}]}},{"id":5,"title":"红烧鲤鱼","score":"6.6","collection":false,"cooked":"13331","titlebg":"/images/fish/9.jpg","detail":{"detailImg":"/images/fish/detail/10.jpg","steps":[{"title":"步骤1","content":"将带皮五花肉斩成麻将块大小，洗净控干水分"},{"title":"步骤2","content":"准备炖肉料，葱切大段，姜切片"},{"title":"步骤3","content":"炒锅倒油，大火，油热后（油锅轻微冒烟），将炖肉料和葱姜下锅，翻炒至出香味 "},{"title":"步骤4","content":"将肉块下锅翻炒"},{"title":"步骤5","content":"炒到变色之后连同炖肉料一起盛出"},{"title":"步骤6","content":"将锅洗净，重新倒油，用最小火，用手抓一把冰糖倒入。用铲子将冰糖铲碎，并不停搅拌。"},{"title":"步骤7","content":"注意观察，见到冰糖全部融化，并开始冒小泡时，把之前炒好的肉连同炖肉料一起重新倒入锅中翻炒。这一步炒糖色别炒过了，否则口感会变苦。我的原则是宁肯没炒到位，那怕看到糖融化就把肉下锅，也别等把糖熬糊了再下锅"},{"title":"步骤8","content":"炒到所有肉块全部上色之后，倒生抽、老抽、料酒，按照3:1:3的比例，再倒入开水（不可倒凉水），液体要没过所有肉"},{"title":"步骤9","content":"转大火，将水烧开，会有很多血沫被煮出来，尽量捞一下，动作要快。然后转小火，加盖焖煮一小时左右。中间注意观察，如果万一水加少了，中途可以加开水，不能加冷水，否则会影响肉的口感"},{"title":"步骤10","content":"煮一小时之后，加盐调味，别加太多，可以尝一下汤的味道。略微淡一点没关系，因为后面收汤时会变咸。如果此时汤少可以继续加热水。再煮半小时左右"},{"title":"步骤11","content":"煮了90分钟之后，转最大火，收汁。在转大火之前，倒入一勺（平时喝汤用的勺）蜂蜜，可以让肉色更加透亮好看。收汁时，要用铲子不停翻炒，让肉块均匀上色，动作要快，因为有糖的缘故，很容易粘锅。注意观察，见到肉块已经变成漂亮的红色就马上关火出锅"}]}},{"id":6,"title":"酸菜鱼","score":"7.5","collection":false,"cooked":"24886","titlebg":"/images/fish/11.jpg","detail":{"detailImg":"/images/fish/detail/12.jpg","steps":[{"title":"步骤1","content":"将带皮五花肉斩成麻将块大小，洗净控干水分"},{"title":"步骤2","content":"准备炖肉料，葱切大段，姜切片"},{"title":"步骤3","content":"炒锅倒油，大火，油热后（油锅轻微冒烟），将炖肉料和葱姜下锅，翻炒至出香味 "},{"title":"步骤4","content":"将肉块下锅翻炒"},{"title":"步骤5","content":"炒到变色之后连同炖肉料一起盛出"},{"title":"步骤6","content":"将锅洗净，重新倒油，用最小火，用手抓一把冰糖倒入。用铲子将冰糖铲碎，并不停搅拌。"},{"title":"步骤7","content":"注意观察，见到冰糖全部融化，并开始冒小泡时，把之前炒好的肉连同炖肉料一起重新倒入锅中翻炒。这一步炒糖色别炒过了，否则口感会变苦。我的原则是宁肯没炒到位，那怕看到糖融化就把肉下锅，也别等把糖熬糊了再下锅"},{"title":"步骤8","content":"炒到所有肉块全部上色之后，倒生抽、老抽、料酒，按照3:1:3的比例，再倒入开水（不可倒凉水），液体要没过所有肉"},{"title":"步骤9","content":"转大火，将水烧开，会有很多血沫被煮出来，尽量捞一下，动作要快。然后转小火，加盖焖煮一小时左右。中间注意观察，如果万一水加少了，中途可以加开水，不能加冷水，否则会影响肉的口感"},{"title":"步骤10","content":"煮一小时之后，加盐调味，别加太多，可以尝一下汤的味道。略微淡一点没关系，因为后面收汤时会变咸。如果此时汤少可以继续加热水。再煮半小时左右"},{"title":"步骤11","content":"煮了90分钟之后，转最大火，收汁。在转大火之前，倒入一勺（平时喝汤用的勺）蜂蜜，可以让肉色更加透亮好看。收汁时，要用铲子不停翻炒，让肉块均匀上色，动作要快，因为有糖的缘故，很容易粘锅。注意观察，见到肉块已经变成漂亮的红色就马上关火出锅"}]}},{"id":7,"title":"水煮鱼","score":"9.5","collection":false,"cooked":"77629","titlebg":"/images/fish/13.jpg","detail":{"detailImg":"/images/fish/detail/14.jpg","steps":[{"title":"步骤1","content":"将带皮五花肉斩成麻将块大小，洗净控干水分"},{"title":"步骤2","content":"准备炖肉料，葱切大段，姜切片"},{"title":"步骤3","content":"炒锅倒油，大火，油热后（油锅轻微冒烟），将炖肉料和葱姜下锅，翻炒至出香味 "},{"title":"步骤4","content":"将肉块下锅翻炒"},{"title":"步骤5","content":"炒到变色之后连同炖肉料一起盛出"},{"title":"步骤6","content":"将锅洗净，重新倒油，用最小火，用手抓一把冰糖倒入。用铲子将冰糖铲碎，并不停搅拌。"},{"title":"步骤7","content":"注意观察，见到冰糖全部融化，并开始冒小泡时，把之前炒好的肉连同炖肉料一起重新倒入锅中翻炒。这一步炒糖色别炒过了，否则口感会变苦。我的原则是宁肯没炒到位，那怕看到糖融化就把肉下锅，也别等把糖熬糊了再下锅"},{"title":"步骤8","content":"炒到所有肉块全部上色之后，倒生抽、老抽、料酒，按照3:1:3的比例，再倒入开水（不可倒凉水），液体要没过所有肉"},{"title":"步骤9","content":"转大火，将水烧开，会有很多血沫被煮出来，尽量捞一下，动作要快。然后转小火，加盖焖煮一小时左右。中间注意观察，如果万一水加少了，中途可以加开水，不能加冷水，否则会影响肉的口感"},{"title":"步骤10","content":"煮一小时之后，加盐调味，别加太多，可以尝一下汤的味道。略微淡一点没关系，因为后面收汤时会变咸。如果此时汤少可以继续加热水。再煮半小时左右"},{"title":"步骤11","content":"煮了90分钟之后，转最大火，收汁。在转大火之前，倒入一勺（平时喝汤用的勺）蜂蜜，可以让肉色更加透亮好看。收汁时，要用铲子不停翻炒，让肉块均匀上色，动作要快，因为有糖的缘故，很容易粘锅。注意观察，见到肉块已经变成漂亮的红色就马上关火出锅"}]}},{"id":8,"title":"鲫鱼豆腐汤","score":"7.3","collection":false,"cooked":"23287","titlebg":"/images/fish/15.jpg","detail":{"detailImg":"/images/fish/detail/16.jpg","steps":[{"title":"步骤1","content":"将带皮五花肉斩成麻将块大小，洗净控干水分"},{"title":"步骤2","content":"准备炖肉料，葱切大段，姜切片"},{"title":"步骤3","content":"炒锅倒油，大火，油热后（油锅轻微冒烟），将炖肉料和葱姜下锅，翻炒至出香味 "},{"title":"步骤4","content":"将肉块下锅翻炒"},{"title":"步骤5","content":"炒到变色之后连同炖肉料一起盛出"},{"title":"步骤6","content":"将锅洗净，重新倒油，用最小火，用手抓一把冰糖倒入。用铲子将冰糖铲碎，并不停搅拌。"},{"title":"步骤7","content":"注意观察，见到冰糖全部融化，并开始冒小泡时，把之前炒好的肉连同炖肉料一起重新倒入锅中翻炒。这一步炒糖色别炒过了，否则口感会变苦。我的原则是宁肯没炒到位，那怕看到糖融化就把肉下锅，也别等把糖熬糊了再下锅"},{"title":"步骤8","content":"炒到所有肉块全部上色之后，倒生抽、老抽、料酒，按照3:1:3的比例，再倒入开水（不可倒凉水），液体要没过所有肉"},{"title":"步骤9","content":"转大火，将水烧开，会有很多血沫被煮出来，尽量捞一下，动作要快。然后转小火，加盖焖煮一小时左右。中间注意观察，如果万一水加少了，中途可以加开水，不能加冷水，否则会影响肉的口感"},{"title":"步骤10","content":"煮一小时之后，加盐调味，别加太多，可以尝一下汤的味道。略微淡一点没关系，因为后面收汤时会变咸。如果此时汤少可以继续加热水。再煮半小时左右"},{"title":"步骤11","content":"煮了90分钟之后，转最大火，收汁。在转大火之前，倒入一勺（平时喝汤用的勺）蜂蜜，可以让肉色更加透亮好看。收汁时，要用铲子不停翻炒，让肉块均匀上色，动作要快，因为有糖的缘故，很容易粘锅。注意观察，见到肉块已经变成漂亮的红色就马上关火出锅"}]}},{"id":9,"title":"孔雀开屏鱼","score":"8.1","collection":false,"cooked":"23287","titlebg":"/images/fish/17.jpg","detail":{"detailImg":"/images/fish/detail/18.jpg","steps":[{"title":"步骤1","content":"将带皮五花肉斩成麻将块大小，洗净控干水分"},{"title":"步骤2","content":"准备炖肉料，葱切大段，姜切片"},{"title":"步骤3","content":"炒锅倒油，大火，油热后（油锅轻微冒烟），将炖肉料和葱姜下锅，翻炒至出香味 "},{"title":"步骤4","content":"将肉块下锅翻炒"},{"title":"步骤5","content":"炒到变色之后连同炖肉料一起盛出"},{"title":"步骤6","content":"将锅洗净，重新倒油，用最小火，用手抓一把冰糖倒入。用铲子将冰糖铲碎，并不停搅拌。"},{"title":"步骤7","content":"注意观察，见到冰糖全部融化，并开始冒小泡时，把之前炒好的肉连同炖肉料一起重新倒入锅中翻炒。这一步炒糖色别炒过了，否则口感会变苦。我的原则是宁肯没炒到位，那怕看到糖融化就把肉下锅，也别等把糖熬糊了再下锅"},{"title":"步骤8","content":"炒到所有肉块全部上色之后，倒生抽、老抽、料酒，按照3:1:3的比例，再倒入开水（不可倒凉水），液体要没过所有肉"},{"title":"步骤9","content":"转大火，将水烧开，会有很多血沫被煮出来，尽量捞一下，动作要快。然后转小火，加盖焖煮一小时左右。中间注意观察，如果万一水加少了，中途可以加开水，不能加冷水，否则会影响肉的口感"},{"title":"步骤10","content":"煮一小时之后，加盐调味，别加太多，可以尝一下汤的味道。略微淡一点没关系，因为后面收汤时会变咸。如果此时汤少可以继续加热水。再煮半小时左右"},{"title":"步骤11","content":"煮了90分钟之后，转最大火，收汁。在转大火之前，倒入一勺（平时喝汤用的勺）蜂蜜，可以让肉色更加透亮好看。收汁时，要用铲子不停翻炒，让肉块均匀上色，动作要快，因为有糖的缘故，很容易粘锅。注意观察，见到肉块已经变成漂亮的红色就马上关火出锅"}]}},{"id":10,"title":"糖醋鱼","score":"7.1","collection":false,"cooked":"23287","titlebg":"/images/fish/19.jpg","detail":{"detailImg":"/images/fish/detail/20.jpg","steps":[{"title":"步骤1","content":"将带皮五花肉斩成麻将块大小，洗净控干水分"},{"title":"步骤2","content":"准备炖肉料，葱切大段，姜切片"},{"title":"步骤3","content":"炒锅倒油，大火，油热后（油锅轻微冒烟），将炖肉料和葱姜下锅，翻炒至出香味 "},{"title":"步骤4","content":"将肉块下锅翻炒"},{"title":"步骤5","content":"炒到变色之后连同炖肉料一起盛出"},{"title":"步骤6","content":"将锅洗净，重新倒油，用最小火，用手抓一把冰糖倒入。用铲子将冰糖铲碎，并不停搅拌。"},{"title":"步骤7","content":"注意观察，见到冰糖全部融化，并开始冒小泡时，把之前炒好的肉连同炖肉料一起重新倒入锅中翻炒。这一步炒糖色别炒过了，否则口感会变苦。我的原则是宁肯没炒到位，那怕看到糖融化就把肉下锅，也别等把糖熬糊了再下锅"},{"title":"步骤8","content":"炒到所有肉块全部上色之后，倒生抽、老抽、料酒，按照3:1:3的比例，再倒入开水（不可倒凉水），液体要没过所有肉"},{"title":"步骤9","content":"转大火，将水烧开，会有很多血沫被煮出来，尽量捞一下，动作要快。然后转小火，加盖焖煮一小时左右。中间注意观察，如果万一水加少了，中途可以加开水，不能加冷水，否则会影响肉的口感"},{"title":"步骤10","content":"煮一小时之后，加盐调味，别加太多，可以尝一下汤的味道。略微淡一点没关系，因为后面收汤时会变咸。如果此时汤少可以继续加热水。再煮半小时左右"},{"title":"步骤11","content":"煮了90分钟之后，转最大火，收汁。在转大火之前，倒入一勺（平时喝汤用的勺）蜂蜜，可以让肉色更加透亮好看。收汁时，要用铲子不停翻炒，让肉块均匀上色，动作要快，因为有糖的缘故，很容易粘锅。注意观察，见到肉块已经变成漂亮的红色就马上关火出锅"}]}}]}